check_shape.py
check_shape-0.2.dist-info/LICENSE
check_shape-0.2.dist-info/METADATA
check_shape-0.2.dist-info/WHEEL
check_shape-0.2.dist-info/top_level.txt
check_shape-0.2.dist-info/RECORD
