Metadata-Version: 2.1
Name: check-shape
Version: 0.2
Summary: A shape checking tool for arrays and tensors
Home-page: https://github.com/stratisMarkou/check-shape
Author: Stratis Markou
Author-email: stratismar@gmail.com
License: UNKNOWN
Project-URL: Bug Tracker, https://github.com/stratisMarkou/check-shape/issues
Platform: UNKNOWN
Classifier: Programming Language :: Python :: 3
Classifier: License :: OSI Approved :: MIT License
Classifier: Operating System :: OS Independent
Requires-Python: >=3.6
